{
    "Numbermoves": "Movimientos",
    "Reset": "Reinicio",
    "esp": "Español",
    "Answer": "Pon tu respuesta",
    "Home": "Inicio",
    "Turn": "Turno",
    "TurnPlayer": "Turno del",
    "Tictactoe": "Tres en raya",
    "Quiz": "Quiz",
    "Submit": "Comprobar",
    "Previous": "Anterior",
    "Next": "Siguiente",
    "en": "Inglés",
    "Score": "Puntuación: ",
    "Ano": "Anónimo",
    "Desp": "Muchas gracias por jugar",
    "Ed": "Tu puntuación ha sido: ",
    "Per": "Con un porcentaje de aciertos del: "
}